{
    "url": "https://static.themarthablog.com/2018/11/Unknown-33-237x300.jpg",
    "key": "000000002512",
    "status": "success",
    "error_message": null,
    "width": 237,
    "height": 300,
    "original_width": 237,
    "original_height": 300,
    "exif": "{\"Image Make\": \"Apple\", \"Image Model\": \"iPhone 6\", \"Image Orientation\": \"Horizontal (normal)\", \"Image XResolution\": \"72\", \"Image YResolution\": \"72\", \"Image ResolutionUnit\": \"Pixels/Inch\", \"Image Software\": \"11.4.1\", \"Image DateTime\": \"2018:11:22 20:20:02\", \"Image YCbCrPositioning\": \"Centered\", \"Image ExifOffset\": \"204\", \"GPS GPSVersionID\": \"[0, 0, 0, 0]\", \"GPS GPSLatitudeRef\": \"N\", \"GPS GPSLatitude\": \"[40, 41, 1289/25]\", \"GPS GPSLongitudeRef\": \"W\", \"GPS GPSLongitude\": \"[73, 56, 331/25]\", \"GPS GPSAltitudeRef\": \"0\", \"GPS GPSAltitude\": \"108637/5100\", \"GPS GPSTimeStamp\": \"[1, 20, 2]\", \"GPS GPSSpeedRef\": \"K\", \"GPS GPSSpeed\": \"19/100\", \"GPS GPSImgDirectionRef\": \"T\", \"GPS GPSImgDirection\": \"33731/368\", \"GPS GPSDestBearingRef\": \"T\", \"GPS GPSDestBearing\": \"33731/368\", \"GPS GPSDate\": \"2018:11:23\", \"GPS Tag 0x001F\": \"25\", \"Image GPSInfo\": \"1702\", \"Thumbnail Compression\": \"JPEG (old-style)\", \"Thumbnail XResolution\": \"72\", \"Thumbnail YResolution\": \"72\", \"Thumbnail ResolutionUnit\": \"Pixels/Inch\", \"Thumbnail JPEGInterchangeFormat\": \"2148\", \"Thumbnail JPEGInterchangeFormatLength\": \"8252\", \"EXIF ExposureTime\": \"1/30\", \"EXIF FNumber\": \"11/5\", \"EXIF ExposureProgram\": \"Program Normal\", \"EXIF ISOSpeedRatings\": \"250\", \"EXIF ExifVersion\": \"\", \"EXIF DateTimeOriginal\": \"2018:11:22 20:20:02\", \"EXIF DateTimeDigitized\": \"2018:11:22 20:20:02\", \"EXIF ComponentsConfiguration\": \"\", \"EXIF ShutterSpeedValue\": \"5845/1191\", \"EXIF ApertureValue\": \"7983/3509\", \"EXIF BrightnessValue\": \"6353/4671\", \"EXIF ExposureBiasValue\": \"0\", \"EXIF MeteringMode\": \"Pattern\", \"EXIF Flash\": \"Flash did not fire, auto mode\", \"EXIF FocalLength\": \"83/20\", \"EXIF SubjectArea\": \"[1631, 1223, 1795, 1077]\", \"EXIF SubSecTimeOriginal\": \"916\", \"EXIF SubSecTimeDigitized\": \"916\", \"EXIF FlashPixVersion\": \"\", \"EXIF ColorSpace\": \"sRGB\", \"EXIF ExifImageWidth\": \"2448\", \"EXIF ExifImageLength\": \"3094\", \"Interoperability InteroperabilityIndex\": \"R98\", \"Interoperability InteroperabilityVersion\": \"[0, 0, 0, 0]\", \"EXIF InteroperabilityOffset\": \"2024\", \"EXIF SensingMethod\": \"One-chip color area\", \"EXIF SceneType\": \"0\", \"EXIF ExposureMode\": \"Auto Exposure\", \"EXIF WhiteBalance\": \"Auto\", \"EXIF FocalLengthIn35mmFilm\": \"29\", \"EXIF SceneCaptureType\": \"Standard\", \"EXIF ImageUniqueID\": \"413b5a276c03a9f60000000000000000\", \"EXIF LensSpecification\": \"[83/20, 83/20, 11/5, 11/5]\", \"EXIF LensMake\": \"Apple\", \"EXIF LensModel\": \"iPhone 6 back camera 4.15mm f/2.2\"}",
    "sha256": "3f7a93782d7d741d0fdc60120f6b9ea713acef551631091ef8ab4d025cddee97"
}