{
    "url": "http://3.bp.blogspot.com/_gv2ZOLiWKJg/TLu-n6cSr8I/AAAAAAAACxg/bVeJO1dE-54/s1600/IMG_0583.JPG",
    "key": "000000003340",
    "status": "success",
    "error_message": null,
    "width": 1394,
    "height": 901,
    "original_width": 1394,
    "original_height": 901,
    "exif": "{\"Image Software\": \"Google\", \"Image YCbCrSubSampling\": \"[2, 2]\", \"Image ExifOffset\": \"58\", \"EXIF ExifVersion\": \"\", \"EXIF DateTimeOriginal\": \"2010:10:17 03:31:23\", \"EXIF ExifImageWidth\": \"1394\", \"EXIF ExifImageLength\": \"901\"}",
    "sha256": "511b3699b061a4919e13f2d14f5e46233bd7b1106410144c1108eb6624acb7cd"
}