{
    "url": "https://thumbs.dreamstime.com/m/dutch-apple-pie-ice-cream-plate-vanilla-36719607.jpg",
    "key": "000000002699",
    "status": "success",
    "error_message": null,
    "width": 120,
    "height": 90,
    "original_width": 120,
    "original_height": 90,
    "exif": "{\"Image XResolution\": \"72\", \"Image YResolution\": \"72\", \"Image ResolutionUnit\": \"Pixels/Inch\", \"Image YCbCrPositioning\": \"Centered\", \"Image Copyright\": \"Shutterbox | Dreamstime.com\"}",
    "sha256": "8a6e05f4ee92f30299184c5ffacef1ab6da9ee1fe708802e55fe0c46337d3aa5"
}