{
    "url": "https://cdn.shopify.com/s/files/1/0066/7929/8113/products/dutch_apple_jam_1024x.jpeg?v=1532722509",
    "key": "000000003295",
    "status": "success",
    "error_message": null,
    "width": 1024,
    "height": 937,
    "original_width": 1024,
    "original_height": 937,
    "exif": "{\"Image Orientation\": \"Horizontal (normal)\", \"Image XResolution\": \"72\", \"Image YResolution\": \"72\", \"Image ResolutionUnit\": \"Pixels/Inch\", \"Image YCbCrPositioning\": \"Centered\", \"Image ExifOffset\": \"102\", \"EXIF ExifVersion\": \"\", \"EXIF ComponentsConfiguration\": \"\", \"EXIF FlashPixVersion\": \"\", \"EXIF ColorSpace\": \"Uncalibrated\", \"EXIF ExifImageWidth\": \"1024\", \"EXIF ExifImageLength\": \"937\"}",
    "sha256": "69c2f758d7479a0fef6018c070eea074c995364bd1c7068851f3f5637c0f43ac"
}