{
    "url": "https://cdn.shopify.com/s/files/1/2461/5069/products/OrangeHazeAmericanFlag1_110x110@2x.jpg?v=1609788470",
    "key": "000000002398",
    "status": "success",
    "error_message": null,
    "width": 220,
    "height": 107,
    "original_width": 220,
    "original_height": 107,
    "exif": "{\"Image Orientation\": \"Horizontal (normal)\", \"Image XResolution\": \"72\", \"Image YResolution\": \"72\", \"Image ResolutionUnit\": \"Pixels/Inch\", \"Image YCbCrPositioning\": \"Centered\", \"Image ExifOffset\": \"102\", \"EXIF ExifVersion\": \"\", \"EXIF ComponentsConfiguration\": \"\", \"EXIF FlashPixVersion\": \"\", \"EXIF ColorSpace\": \"Uncalibrated\", \"EXIF ExifImageWidth\": \"220\", \"EXIF ExifImageLength\": \"107\"}",
    "sha256": "2a487bcea9eaadd670d88697ec641e1524744685f232df73adeb9ec7935b7681"
}